pyasn1_modules/__init__.py
pyasn1_modules/pem.py
pyasn1_modules/rfc1155.py
pyasn1_modules/rfc1157.py
pyasn1_modules/rfc1901.py
pyasn1_modules/rfc1902.py
pyasn1_modules/rfc1905.py
pyasn1_modules/rfc2251.py
pyasn1_modules/rfc2314.py
pyasn1_modules/rfc2315.py
pyasn1_modules/rfc2437.py
pyasn1_modules/rfc2459.py
pyasn1_modules/rfc2511.py
pyasn1_modules/rfc2560.py
pyasn1_modules/rfc2634.py
pyasn1_modules/rfc2985.py
pyasn1_modules/rfc2986.py
pyasn1_modules/rfc3161.py
pyasn1_modules/rfc3274.py
pyasn1_modules/rfc3279.py
pyasn1_modules/rfc3280.py
pyasn1_modules/rfc3281.py
pyasn1_modules/rfc3412.py
pyasn1_modules/rfc3414.py
pyasn1_modules/rfc3447.py
pyasn1_modules/rfc3560.py
pyasn1_modules/rfc3565.py
pyasn1_modules/rfc3709.py
pyasn1_modules/rfc3770.py
pyasn1_modules/rfc3779.py
pyasn1_modules/rfc3852.py
pyasn1_modules/rfc4055.py
pyasn1_modules/rfc4073.py
pyasn1_modules/rfc4108.py
pyasn1_modules/rfc4210.py
pyasn1_modules/rfc4211.py
pyasn1_modules/rfc5035.py
pyasn1_modules/rfc5083.py
pyasn1_modules/rfc5084.py
pyasn1_modules/rfc5208.py
pyasn1_modules/rfc5280.py
pyasn1_modules/rfc5480.py
pyasn1_modules/rfc5649.py
pyasn1_modules/rfc5652.py
pyasn1_modules/rfc5751.py
pyasn1_modules/rfc5914.py
pyasn1_modules/rfc5915.py
pyasn1_modules/rfc5934.py
pyasn1_modules/rfc5940.py
pyasn1_modules/rfc5958.py
pyasn1_modules/rfc5990.py
pyasn1_modules/rfc6010.py
pyasn1_modules/rfc6019.py
pyasn1_modules/rfc6031.py
pyasn1_modules/rfc6032.py
pyasn1_modules/rfc6210.py
pyasn1_modules/rfc6211.py
pyasn1_modules/rfc6402.py
pyasn1_modules/rfc7030.py
pyasn1_modules/rfc7191.py
pyasn1_modules/rfc7292.py
pyasn1_modules/rfc7296.py
pyasn1_modules/rfc7773.py
pyasn1_modules/rfc7894.py
pyasn1_modules/rfc7906.py
pyasn1_modules/rfc7914.py
pyasn1_modules/rfc8017.py
pyasn1_modules/rfc8018.py
pyasn1_modules/rfc8103.py
pyasn1_modules/rfc8209.py
pyasn1_modules/rfc8226.py
pyasn1_modules/rfc8358.py
pyasn1_modules/rfc8360.py
pyasn1_modules/rfc8398.py
pyasn1_modules-0.2.7.dist-info/DESCRIPTION.rst
pyasn1_modules-0.2.7.dist-info/LICENSE.txt
pyasn1_modules-0.2.7.dist-info/METADATA
pyasn1_modules-0.2.7.dist-info/RECORD
pyasn1_modules-0.2.7.dist-info/WHEEL
pyasn1_modules-0.2.7.dist-info/metadata.json
pyasn1_modules-0.2.7.dist-info/top_level.txt
pyasn1_modules-0.2.7.dist-info/zip-safe
